date_normalization/__init__.py
date_normalization/datenormalization.py
date_normalization/datestandard.py
date_normalization/gregoriandatenormalization.py
date_normalization/jalaliandatenormalization.py
date_normalization/publicnormalization.py
nlp_date_normalization_snd-0.1.2.dist-info/LICENSE
nlp_date_normalization_snd-0.1.2.dist-info/METADATA
nlp_date_normalization_snd-0.1.2.dist-info/WHEEL
nlp_date_normalization_snd-0.1.2.dist-info/top_level.txt
nlp_date_normalization_snd-0.1.2.dist-info/RECORD
