Metadata-Version: 2.1
Name: nlp_date_normalization_snd
Version: 0.1.2
Summary: This library is part of the NLP project which analyzes the Persian text given to it and extracts all Jalalian and Gregorian dates and converts them into a standard format in Gregorian date.
Home-page: https://github.com/7cloner/NLP-Date-Normalization-SND-
Author: Nasser Khaledi
Author-email: foray00227@gmail.com
Classifier: Programming Language :: Python :: 3
Classifier: License :: OSI Approved :: MIT License
Classifier: Operating System :: OS Independent
Requires-Python: >=3.6
License-File: LICENSE
Requires-Dist: jdatetime
